{
  "_class": "sharedStyle",
  "do_objectID": "1B63662D-E881-41CD-BDE3-8B48BE1AE997",
  "name": "BBB / colors / greyExtraLight",
  "value": {
    "_class": "style",
    "borders": [
      {
        "_class": "border",
        "color": {
          "_class": "color",
          "alpha": 1,
          "blue": 0.592,
          "green": 0.592,
          "red": 0.592
        },
        "fillType": 0,
        "isEnabled": false,
        "position": 1,
        "thickness": 1
      }
    ],
    "endDecorationType": 0,
    "fills": [
      {
        "_class": "fill",
        "color": {
          "_class": "color",
          "alpha": 1,
          "blue": 0.9803921568627451,
          "green": 0.9803921568627451,
          "red": 0.9803921568627451
        },
        "fillType": 0,
        "isEnabled": true,
        "noiseIndex": 0,
        "noiseIntensity": 0,
        "patternFillType": 0,
        "patternTileScale": 1
      }
    ],
    "miterLimit": 10,
    "sharedObjectID": "1B63662D-E881-41CD-BDE3-8B48BE1AE997",
    "startDecorationType": 0
  }
}