{
  "_class": "group",
  "do_objectID": "38DFA26C-5029-4C00-95BF-3C5B031BF376",
  "exportOptions": {
    "_class": "exportOptions",
    "exportFormats": [
    ],
    "includedLayerIds": [
    ],
    "layerOptions": 0,
    "shouldTrim": false
  },
  "frame": {
    "_class": "rect",
    "constrainProportions": false,
    "height": 12,
    "width": 18,
    "x": 1,
    "y": 4
  },
  "hasClickThrough": false,
  "isFlippedHorizontal": false,
  "isFlippedVertical": false,
  "isLocked": false,
  "isVisible": true,
  "layerListExpandedType": 0,
  "layers": [
    {
      "class": "shapeGroup",
      "id": "E59A9B29-F09A-4AC8-93BD-F5FBEDCFEFEB"
    },
    {
      "class": "symbolInstance",
      "id": "C50B4D46-9D5E-4E88-B3E3-3AFCC39C88D1"
    }
  ],
  "name": "Shape",
  "nameIsFixed": true,
  "resizingConstraint": 63,
  "resizingType": 0,
  "rotation": 0,
  "shouldBreakMaskChain": false,
  "style": {
    "_class": "style",
    "endDecorationType": 0,
    "miterLimit": 10,
    "startDecorationType": 0
  }
}