{
  "_class": "shapePath",
  "booleanOperation": -1,
  "do_objectID": "677ABD04-A170-4B33-9942-A860C4A175E0",
  "edited": true,
  "exportOptions": {
    "_class": "exportOptions",
    "exportFormats": [
    ],
    "includedLayerIds": [
    ],
    "layerOptions": 0,
    "shouldTrim": false
  },
  "frame": {
    "_class": "rect",
    "constrainProportions": false,
    "height": 4.031955104318504,
    "width": 3.929791631356148,
    "x": 15.4015833415146,
    "y": 15.96804489568145
  },
  "isFlippedHorizontal": false,
  "isFlippedVertical": false,
  "isLocked": false,
  "isVisible": true,
  "layerListExpandedType": 0,
  "name": "Stroke 1",
  "nameIsFixed": false,
  "path": {
    "_class": "path",
    "isClosed": true,
    "pointRadiusBehaviour": 1,
    "points": [
      {
        "_class": "curvePoint",
        "cornerRadius": 0,
        "curveFrom": "{0, 0.22211485286063451}",
        "curveMode": 2,
        "curveTo": "{0, 0.77788514713936507}",
        "hasCurveFrom": true,
        "hasCurveTo": true,
        "point": "{0, 0.50000000000000022}"
      },
      {
        "_class": "curvePoint",
        "cornerRadius": 0,
        "curveFrom": "{0.77450723254898923, 0}",
        "curveMode": 2,
        "curveTo": "{0.22545793714408605, 0}",
        "hasCurveFrom": true,
        "hasCurveTo": true,
        "point": "{0.49991349979816579, 0}"
      },
      {
        "_class": "curvePoint",
        "cornerRadius": 0,
        "curveFrom": "{1, 0.77792115591850808}",
        "curveMode": 2,
        "curveTo": "{1, 0.22207884408149065}",
        "hasCurveFrom": true,
        "hasCurveTo": true,
        "point": "{1, 0.50000000000000022}"
      },
      {
        "_class": "curvePoint",
        "cornerRadius": 0,
        "curveFrom": "{0.22545793714408688, 1}",
        "curveMode": 2,
        "curveTo": "{0.77450723254898757, 1}",
        "hasCurveFrom": true,
        "hasCurveTo": true,
        "point": "{0.49991349979816579, 1}"
      }
    ]
  },
  "resizingConstraint": 63,
  "resizingType": 0,
  "rotation": 0,
  "shouldBreakMaskChain": false
}